{
  "executed_at": "2026-04-02T16:30:39.486402+00:00",
  "mode": "yolov8",
  "image_path": "vision/storage/artifacts/2026/04/02/snapshot_20260402T163012137203Z.jpg",
  "lote_id": null,
  "capture_metadata": {
    "captured_at": "2026-04-02T16:30:12.133152+00:00",
    "camera_url": "https://cam.cogumelos.net/capture",
    "http_status": 200,
    "content_type": "image/jpeg",
    "size_bytes": 44093,
    "source": "esp32-cam",
    "capture_attempt": 1,
    "capture_attempts_total": 3,
    "request_timeout_seconds": 15
  },
  "quality_check": {
    "status": "valid",
    "dataset_eligible": true,
    "metrics": {
      "resolution": {
        "width": 800,
        "height": 600,
        "total_pixels": 480000
      },
      "brightness_mean": 67.69,
      "contrast_stddev": 60.84,
      "sharpness_score": 12.2
    },
    "flags": {
      "low_resolution": false,
      "too_dark": false,
      "too_bright": false,
      "too_blurry": false,
      "invalid_image": false
    },
    "thresholds": {
      "min_width": 640,
      "min_height": 480,
      "too_dark_below": 55.0,
      "too_bright_above": 210.0,
      "too_blurry_below": 12.0
    },
    "error": null
  },
  "block_detection": {
    "enabled": true,
    "model": "/home/shroom/workspace/shroom-app/vision/models/block_detector_v2.pt",
    "model_path": "/home/shroom/workspace/shroom-app/vision/models/block_detector_v2.pt",
    "model_version": "v2",
    "used_fallback": false,
    "requested_model_path": "/home/shroom/workspace/shroom-app/vision/models/block_detector_v2.pt",
    "fallback_model_path": "/home/shroom/workspace/shroom-app/vision/models/block_detector.pt",
    "device": "cpu",
    "blocos_detectados": 18,
    "detections": [
      {
        "label": "bloco",
        "confidence": 0.8491,
        "bbox": [
          251.07,
          0.0,
          348.25,
          124.19
        ]
      },
      {
        "label": "bloco",
        "confidence": 0.8453,
        "bbox": [
          0.64,
          2.53,
          81.86,
          182.91
        ]
      },
      {
        "label": "bloco",
        "confidence": 0.824,
        "bbox": [
          52.52,
          1.42,
          170.45,
          170.56
        ]
      },
      {
        "label": "bloco",
        "confidence": 0.8085,
        "bbox": [
          366.36,
          97.26,
          451.96,
          262.35
        ]
      },
      {
        "label": "bloco",
        "confidence": 0.7522,
        "bbox": [
          285.19,
          123.0,
          374.23,
          281.52
        ]
      },
      {
        "label": "bloco",
        "confidence": 0.7228,
        "bbox": [
          4.84,
          199.89,
          123.3,
          349.23
        ]
      },
      {
        "label": "bloco",
        "confidence": 0.718,
        "bbox": [
          339.33,
          0.0,
          434.34,
          105.23
        ]
      },
      {
        "label": "bloco",
        "confidence": 0.7169,
        "bbox": [
          433.43,
          83.43,
          529.19,
          229.01
        ]
      },
      {
        "label": "bloco",
        "confidence": 0.6632,
        "bbox": [
          146.66,
          0.45,
          255.13,
          145.35
        ]
      },
      {
        "label": "bloco",
        "confidence": 0.628,
        "bbox": [
          305.16,
          362.05,
          386.72,
          464.49
        ]
      },
      {
        "label": "bloco",
        "confidence": 0.5915,
        "bbox": [
          202.01,
          164.0,
          297.31,
          297.97
        ]
      },
      {
        "label": "bloco",
        "confidence": 0.4432,
        "bbox": [
          342.46,
          270.99,
          404.87,
          362.56
        ]
      },
      {
        "label": "bloco",
        "confidence": 0.44,
        "bbox": [
          428.22,
          0.0,
          505.98,
          82.49
        ]
      },
      {
        "label": "bloco",
        "confidence": 0.4383,
        "bbox": [
          107.59,
          185.76,
          209.81,
          338.77
        ]
      },
      {
        "label": "bloco",
        "confidence": 0.4245,
        "bbox": [
          401.98,
          251.55,
          462.21,
          402.83
        ]
      },
      {
        "label": "bloco",
        "confidence": 0.3935,
        "bbox": [
          296.39,
          298.02,
          344.5,
          358.95
        ]
      },
      {
        "label": "bloco",
        "confidence": 0.3066,
        "bbox": [
          405.68,
          310.16,
          456.21,
          403.52
        ]
      },
      {
        "label": "bloco",
        "confidence": 0.3002,
        "bbox": [
          398.59,
          254.07,
          463.6,
          358.11
        ]
      }
    ],
    "error": null,
    "python_executable": "/home/shroom/workspace/shroom-app/.venv311/bin/python3",
    "python_version": "3.11.9 (main, Mar 18 2026, 22:08:28) [GCC 14.2.0]"
  },
  "summary": {
    "lote_id": null,
    "blocos_detectados": 18,
    "confianca_media_blocos": 0.6037,
    "block_detection_error": null,
    "contaminacao_visual_detectada": false,
    "colonizacao_estimada": null,
    "quality_status": "valid",
    "dataset_eligible": true,
    "dataset_class": "valid",
    "remote_persisted": true
  },
  "detections": [
    {
      "label": "bloco",
      "confidence": 0.8491,
      "bbox": [
        251.07,
        0.0,
        348.25,
        124.19
      ]
    },
    {
      "label": "bloco",
      "confidence": 0.8453,
      "bbox": [
        0.64,
        2.53,
        81.86,
        182.91
      ]
    },
    {
      "label": "bloco",
      "confidence": 0.824,
      "bbox": [
        52.52,
        1.42,
        170.45,
        170.56
      ]
    },
    {
      "label": "bloco",
      "confidence": 0.8085,
      "bbox": [
        366.36,
        97.26,
        451.96,
        262.35
      ]
    },
    {
      "label": "bloco",
      "confidence": 0.7522,
      "bbox": [
        285.19,
        123.0,
        374.23,
        281.52
      ]
    },
    {
      "label": "bloco",
      "confidence": 0.7228,
      "bbox": [
        4.84,
        199.89,
        123.3,
        349.23
      ]
    },
    {
      "label": "bloco",
      "confidence": 0.718,
      "bbox": [
        339.33,
        0.0,
        434.34,
        105.23
      ]
    },
    {
      "label": "bloco",
      "confidence": 0.7169,
      "bbox": [
        433.43,
        83.43,
        529.19,
        229.01
      ]
    },
    {
      "label": "bloco",
      "confidence": 0.6632,
      "bbox": [
        146.66,
        0.45,
        255.13,
        145.35
      ]
    },
    {
      "label": "bloco",
      "confidence": 0.628,
      "bbox": [
        305.16,
        362.05,
        386.72,
        464.49
      ]
    },
    {
      "label": "bloco",
      "confidence": 0.5915,
      "bbox": [
        202.01,
        164.0,
        297.31,
        297.97
      ]
    },
    {
      "label": "bloco",
      "confidence": 0.4432,
      "bbox": [
        342.46,
        270.99,
        404.87,
        362.56
      ]
    },
    {
      "label": "bloco",
      "confidence": 0.44,
      "bbox": [
        428.22,
        0.0,
        505.98,
        82.49
      ]
    },
    {
      "label": "bloco",
      "confidence": 0.4383,
      "bbox": [
        107.59,
        185.76,
        209.81,
        338.77
      ]
    },
    {
      "label": "bloco",
      "confidence": 0.4245,
      "bbox": [
        401.98,
        251.55,
        462.21,
        402.83
      ]
    },
    {
      "label": "bloco",
      "confidence": 0.3935,
      "bbox": [
        296.39,
        298.02,
        344.5,
        358.95
      ]
    },
    {
      "label": "bloco",
      "confidence": 0.3066,
      "bbox": [
        405.68,
        310.16,
        456.21,
        403.52
      ]
    },
    {
      "label": "bloco",
      "confidence": 0.3002,
      "bbox": [
        398.59,
        254.07,
        463.6,
        358.11
      ]
    }
  ],
  "notes": [
    "Pipeline executado com quality check local e detector inicial de blocos.",
    "A deteccao de colonizacao e contaminacao_visual ainda nao esta implementada.",
    "Se o modelo YOLO nao existir, a deteccao retorna lista vazia sem quebrar o fluxo."
  ],
  "target_labels": [
    "bloco",
    "colonizacao",
    "contaminacao_visual"
  ],
  "dataset_classification": {
    "enabled": true,
    "applied": true,
    "dataset_class": "valid",
    "quality_status": "valid",
    "dataset_eligible": true,
    "target_image_path": "vision/dataset/raw/valid/snapshot_20260402T163012137203Z.jpg",
    "target_metadata_path": "vision/dataset/raw/valid/snapshot_20260402T163012137203Z.json",
    "method": "hardlink",
    "error": null
  },
  "remote_persistence": {
    "enabled": true,
    "remote_persisted": true,
    "storage_uploaded": true,
    "db_record_created": true,
    "image_storage_path": "vision/captures/2026/04/02/snapshot_20260402T163012137203Z.jpg",
    "record_id": "f2a13364-137b-4f5e-9393-201164491334",
    "db_table": "vision_pipeline_runs",
    "retry_manifest_path": null,
    "error": null
  },
  "remote_persisted": true,
  "storage_uploaded": true,
  "db_record_created": true
}