{
  "executed_at": "2026-03-31T00:30:40.249580+00:00",
  "mode": "yolov8",
  "image_path": "vision/storage/artifacts/2026/03/31/snapshot_20260331T003012742539Z.jpg",
  "lote_id": null,
  "capture_metadata": {
    "captured_at": "2026-03-31T00:30:12.738896+00:00",
    "camera_url": "https://cam.cogumelos.net/capture",
    "http_status": 200,
    "content_type": "image/jpeg",
    "size_bytes": 44634,
    "source": "esp32-cam",
    "capture_attempt": 1,
    "capture_attempts_total": 3,
    "request_timeout_seconds": 15
  },
  "quality_check": {
    "status": "valid",
    "dataset_eligible": true,
    "metrics": {
      "resolution": {
        "width": 800,
        "height": 600,
        "total_pixels": 480000
      },
      "brightness_mean": 70.5,
      "contrast_stddev": 63.76,
      "sharpness_score": 12.77
    },
    "flags": {
      "low_resolution": false,
      "too_dark": false,
      "too_bright": false,
      "too_blurry": false,
      "invalid_image": false
    },
    "thresholds": {
      "min_width": 640,
      "min_height": 480,
      "too_dark_below": 55.0,
      "too_bright_above": 210.0,
      "too_blurry_below": 12.0
    },
    "error": null
  },
  "block_detection": {
    "enabled": true,
    "model": "/home/shroom/workspace/shroom-app/vision/models/block_detector_v2.pt",
    "model_path": "/home/shroom/workspace/shroom-app/vision/models/block_detector_v2.pt",
    "model_version": "v2",
    "used_fallback": false,
    "requested_model_path": "/home/shroom/workspace/shroom-app/vision/models/block_detector_v2.pt",
    "fallback_model_path": "/home/shroom/workspace/shroom-app/vision/models/block_detector.pt",
    "device": "cpu",
    "blocos_detectados": 15,
    "detections": [
      {
        "label": "bloco",
        "confidence": 0.9568,
        "bbox": [
          1.03,
          2.69,
          139.53,
          159.67
        ]
      },
      {
        "label": "bloco",
        "confidence": 0.8438,
        "bbox": [
          242.16,
          0.0,
          352.06,
          121.56
        ]
      },
      {
        "label": "bloco",
        "confidence": 0.8273,
        "bbox": [
          430.76,
          77.79,
          525.18,
          237.82
        ]
      },
      {
        "label": "bloco",
        "confidence": 0.8006,
        "bbox": [
          363.09,
          80.41,
          443.89,
          251.02
        ]
      },
      {
        "label": "bloco",
        "confidence": 0.7585,
        "bbox": [
          286.31,
          143.05,
          374.1,
          279.56
        ]
      },
      {
        "label": "bloco",
        "confidence": 0.6461,
        "bbox": [
          115.16,
          1.53,
          234.02,
          153.64
        ]
      },
      {
        "label": "bloco",
        "confidence": 0.5848,
        "bbox": [
          208.01,
          116.17,
          297.26,
          298.44
        ]
      },
      {
        "label": "bloco",
        "confidence": 0.5597,
        "bbox": [
          451.38,
          227.46,
          541.44,
          347.27
        ]
      },
      {
        "label": "bloco",
        "confidence": 0.5464,
        "bbox": [
          415.7,
          0.0,
          508.57,
          83.64
        ]
      },
      {
        "label": "bloco",
        "confidence": 0.4904,
        "bbox": [
          5.26,
          201.83,
          126.86,
          350.82
        ]
      },
      {
        "label": "bloco",
        "confidence": 0.4406,
        "bbox": [
          307.51,
          289.44,
          357.4,
          352.87
        ]
      },
      {
        "label": "bloco",
        "confidence": 0.335,
        "bbox": [
          349.09,
          260.04,
          407.66,
          382.27
        ]
      },
      {
        "label": "bloco",
        "confidence": 0.2764,
        "bbox": [
          72.33,
          350.62,
          156.65,
          456.94
        ]
      },
      {
        "label": "bloco",
        "confidence": 0.2721,
        "bbox": [
          107.41,
          180.39,
          209.04,
          330.0
        ]
      },
      {
        "label": "bloco",
        "confidence": 0.2573,
        "bbox": [
          399.46,
          266.0,
          478.27,
          362.45
        ]
      }
    ],
    "error": null,
    "python_executable": "/home/shroom/workspace/shroom-app/.venv311/bin/python3",
    "python_version": "3.11.9 (main, Mar 18 2026, 22:08:28) [GCC 14.2.0]"
  },
  "summary": {
    "lote_id": null,
    "blocos_detectados": 15,
    "confianca_media_blocos": 0.5731,
    "block_detection_error": null,
    "contaminacao_visual_detectada": false,
    "colonizacao_estimada": null,
    "quality_status": "valid",
    "dataset_eligible": true,
    "dataset_class": "valid",
    "remote_persisted": true
  },
  "detections": [
    {
      "label": "bloco",
      "confidence": 0.9568,
      "bbox": [
        1.03,
        2.69,
        139.53,
        159.67
      ]
    },
    {
      "label": "bloco",
      "confidence": 0.8438,
      "bbox": [
        242.16,
        0.0,
        352.06,
        121.56
      ]
    },
    {
      "label": "bloco",
      "confidence": 0.8273,
      "bbox": [
        430.76,
        77.79,
        525.18,
        237.82
      ]
    },
    {
      "label": "bloco",
      "confidence": 0.8006,
      "bbox": [
        363.09,
        80.41,
        443.89,
        251.02
      ]
    },
    {
      "label": "bloco",
      "confidence": 0.7585,
      "bbox": [
        286.31,
        143.05,
        374.1,
        279.56
      ]
    },
    {
      "label": "bloco",
      "confidence": 0.6461,
      "bbox": [
        115.16,
        1.53,
        234.02,
        153.64
      ]
    },
    {
      "label": "bloco",
      "confidence": 0.5848,
      "bbox": [
        208.01,
        116.17,
        297.26,
        298.44
      ]
    },
    {
      "label": "bloco",
      "confidence": 0.5597,
      "bbox": [
        451.38,
        227.46,
        541.44,
        347.27
      ]
    },
    {
      "label": "bloco",
      "confidence": 0.5464,
      "bbox": [
        415.7,
        0.0,
        508.57,
        83.64
      ]
    },
    {
      "label": "bloco",
      "confidence": 0.4904,
      "bbox": [
        5.26,
        201.83,
        126.86,
        350.82
      ]
    },
    {
      "label": "bloco",
      "confidence": 0.4406,
      "bbox": [
        307.51,
        289.44,
        357.4,
        352.87
      ]
    },
    {
      "label": "bloco",
      "confidence": 0.335,
      "bbox": [
        349.09,
        260.04,
        407.66,
        382.27
      ]
    },
    {
      "label": "bloco",
      "confidence": 0.2764,
      "bbox": [
        72.33,
        350.62,
        156.65,
        456.94
      ]
    },
    {
      "label": "bloco",
      "confidence": 0.2721,
      "bbox": [
        107.41,
        180.39,
        209.04,
        330.0
      ]
    },
    {
      "label": "bloco",
      "confidence": 0.2573,
      "bbox": [
        399.46,
        266.0,
        478.27,
        362.45
      ]
    }
  ],
  "notes": [
    "Pipeline executado com quality check local e detector inicial de blocos.",
    "A deteccao de colonizacao e contaminacao_visual ainda nao esta implementada.",
    "Se o modelo YOLO nao existir, a deteccao retorna lista vazia sem quebrar o fluxo."
  ],
  "target_labels": [
    "bloco",
    "colonizacao",
    "contaminacao_visual"
  ],
  "dataset_classification": {
    "enabled": true,
    "applied": true,
    "dataset_class": "valid",
    "quality_status": "valid",
    "dataset_eligible": true,
    "target_image_path": "vision/dataset/raw/valid/snapshot_20260331T003012742539Z.jpg",
    "target_metadata_path": "vision/dataset/raw/valid/snapshot_20260331T003012742539Z.json",
    "method": "hardlink",
    "error": null
  },
  "remote_persistence": {
    "enabled": true,
    "remote_persisted": true,
    "storage_uploaded": true,
    "db_record_created": true,
    "image_storage_path": "vision/captures/2026/03/31/snapshot_20260331T003012742539Z.jpg",
    "record_id": "0af40f5d-934a-4034-a749-d1db58b7afad",
    "db_table": "vision_pipeline_runs",
    "retry_manifest_path": null,
    "error": null
  },
  "remote_persisted": true,
  "storage_uploaded": true,
  "db_record_created": true
}