{
  "executed_at": "2026-04-03T03:20:39.178427+00:00",
  "mode": "yolov8",
  "image_path": "vision/storage/artifacts/2026/04/03/snapshot_20260403T032011804645Z.jpg",
  "lote_id": null,
  "capture_metadata": {
    "captured_at": "2026-04-03T03:20:11.797541+00:00",
    "camera_url": "https://cam.cogumelos.net/capture",
    "http_status": 200,
    "content_type": "image/jpeg",
    "size_bytes": 43962,
    "source": "esp32-cam",
    "capture_attempt": 1,
    "capture_attempts_total": 3,
    "request_timeout_seconds": 15
  },
  "quality_check": {
    "status": "valid",
    "dataset_eligible": true,
    "metrics": {
      "resolution": {
        "width": 800,
        "height": 600,
        "total_pixels": 480000
      },
      "brightness_mean": 66.74,
      "contrast_stddev": 61.02,
      "sharpness_score": 12.19
    },
    "flags": {
      "low_resolution": false,
      "too_dark": false,
      "too_bright": false,
      "too_blurry": false,
      "invalid_image": false
    },
    "thresholds": {
      "min_width": 640,
      "min_height": 480,
      "too_dark_below": 55.0,
      "too_bright_above": 210.0,
      "too_blurry_below": 12.0
    },
    "error": null
  },
  "block_detection": {
    "enabled": true,
    "model": "/home/shroom/workspace/shroom-app/vision/models/block_detector_v2.pt",
    "model_path": "/home/shroom/workspace/shroom-app/vision/models/block_detector_v2.pt",
    "model_version": "v2",
    "used_fallback": false,
    "requested_model_path": "/home/shroom/workspace/shroom-app/vision/models/block_detector_v2.pt",
    "fallback_model_path": "/home/shroom/workspace/shroom-app/vision/models/block_detector.pt",
    "device": "cpu",
    "blocos_detectados": 18,
    "detections": [
      {
        "label": "bloco",
        "confidence": 0.8511,
        "bbox": [
          0.65,
          2.65,
          82.2,
          182.18
        ]
      },
      {
        "label": "bloco",
        "confidence": 0.8444,
        "bbox": [
          250.58,
          0.0,
          345.84,
          122.81
        ]
      },
      {
        "label": "bloco",
        "confidence": 0.8037,
        "bbox": [
          49.18,
          1.34,
          169.54,
          170.21
        ]
      },
      {
        "label": "bloco",
        "confidence": 0.7617,
        "bbox": [
          365.86,
          97.72,
          442.66,
          265.45
        ]
      },
      {
        "label": "bloco",
        "confidence": 0.7412,
        "bbox": [
          284.86,
          128.76,
          371.79,
          281.29
        ]
      },
      {
        "label": "bloco",
        "confidence": 0.7334,
        "bbox": [
          338.61,
          0.0,
          435.05,
          106.67
        ]
      },
      {
        "label": "bloco",
        "confidence": 0.729,
        "bbox": [
          431.56,
          83.33,
          526.47,
          231.69
        ]
      },
      {
        "label": "bloco",
        "confidence": 0.7198,
        "bbox": [
          5.48,
          199.66,
          122.59,
          351.02
        ]
      },
      {
        "label": "bloco",
        "confidence": 0.6831,
        "bbox": [
          145.83,
          0.63,
          256.56,
          145.12
        ]
      },
      {
        "label": "bloco",
        "confidence": 0.6649,
        "bbox": [
          303.96,
          360.99,
          385.36,
          463.01
        ]
      },
      {
        "label": "bloco",
        "confidence": 0.6191,
        "bbox": [
          108.83,
          186.66,
          209.93,
          336.9
        ]
      },
      {
        "label": "bloco",
        "confidence": 0.6135,
        "bbox": [
          203.64,
          161.6,
          296.56,
          299.22
        ]
      },
      {
        "label": "bloco",
        "confidence": 0.609,
        "bbox": [
          424.94,
          0.0,
          508.32,
          83.75
        ]
      },
      {
        "label": "bloco",
        "confidence": 0.4617,
        "bbox": [
          478.48,
          364.05,
          532.09,
          434.83
        ]
      },
      {
        "label": "bloco",
        "confidence": 0.4332,
        "bbox": [
          341.6,
          274.71,
          404.3,
          364.37
        ]
      },
      {
        "label": "bloco",
        "confidence": 0.3527,
        "bbox": [
          395.78,
          254.37,
          462.53,
          337.35
        ]
      },
      {
        "label": "bloco",
        "confidence": 0.3275,
        "bbox": [
          405.07,
          311.96,
          455.64,
          402.86
        ]
      },
      {
        "label": "bloco",
        "confidence": 0.2591,
        "bbox": [
          298.11,
          294.52,
          343.76,
          361.52
        ]
      }
    ],
    "error": null,
    "python_executable": "/home/shroom/workspace/shroom-app/.venv311/bin/python3",
    "python_version": "3.11.9 (main, Mar 18 2026, 22:08:28) [GCC 14.2.0]"
  },
  "summary": {
    "lote_id": null,
    "blocos_detectados": 18,
    "confianca_media_blocos": 0.6227,
    "block_detection_error": null,
    "contaminacao_visual_detectada": false,
    "colonizacao_estimada": null,
    "quality_status": "valid",
    "dataset_eligible": true,
    "dataset_class": "valid",
    "remote_persisted": true
  },
  "detections": [
    {
      "label": "bloco",
      "confidence": 0.8511,
      "bbox": [
        0.65,
        2.65,
        82.2,
        182.18
      ]
    },
    {
      "label": "bloco",
      "confidence": 0.8444,
      "bbox": [
        250.58,
        0.0,
        345.84,
        122.81
      ]
    },
    {
      "label": "bloco",
      "confidence": 0.8037,
      "bbox": [
        49.18,
        1.34,
        169.54,
        170.21
      ]
    },
    {
      "label": "bloco",
      "confidence": 0.7617,
      "bbox": [
        365.86,
        97.72,
        442.66,
        265.45
      ]
    },
    {
      "label": "bloco",
      "confidence": 0.7412,
      "bbox": [
        284.86,
        128.76,
        371.79,
        281.29
      ]
    },
    {
      "label": "bloco",
      "confidence": 0.7334,
      "bbox": [
        338.61,
        0.0,
        435.05,
        106.67
      ]
    },
    {
      "label": "bloco",
      "confidence": 0.729,
      "bbox": [
        431.56,
        83.33,
        526.47,
        231.69
      ]
    },
    {
      "label": "bloco",
      "confidence": 0.7198,
      "bbox": [
        5.48,
        199.66,
        122.59,
        351.02
      ]
    },
    {
      "label": "bloco",
      "confidence": 0.6831,
      "bbox": [
        145.83,
        0.63,
        256.56,
        145.12
      ]
    },
    {
      "label": "bloco",
      "confidence": 0.6649,
      "bbox": [
        303.96,
        360.99,
        385.36,
        463.01
      ]
    },
    {
      "label": "bloco",
      "confidence": 0.6191,
      "bbox": [
        108.83,
        186.66,
        209.93,
        336.9
      ]
    },
    {
      "label": "bloco",
      "confidence": 0.6135,
      "bbox": [
        203.64,
        161.6,
        296.56,
        299.22
      ]
    },
    {
      "label": "bloco",
      "confidence": 0.609,
      "bbox": [
        424.94,
        0.0,
        508.32,
        83.75
      ]
    },
    {
      "label": "bloco",
      "confidence": 0.4617,
      "bbox": [
        478.48,
        364.05,
        532.09,
        434.83
      ]
    },
    {
      "label": "bloco",
      "confidence": 0.4332,
      "bbox": [
        341.6,
        274.71,
        404.3,
        364.37
      ]
    },
    {
      "label": "bloco",
      "confidence": 0.3527,
      "bbox": [
        395.78,
        254.37,
        462.53,
        337.35
      ]
    },
    {
      "label": "bloco",
      "confidence": 0.3275,
      "bbox": [
        405.07,
        311.96,
        455.64,
        402.86
      ]
    },
    {
      "label": "bloco",
      "confidence": 0.2591,
      "bbox": [
        298.11,
        294.52,
        343.76,
        361.52
      ]
    }
  ],
  "notes": [
    "Pipeline executado com quality check local e detector inicial de blocos.",
    "A deteccao de colonizacao e contaminacao_visual ainda nao esta implementada.",
    "Se o modelo YOLO nao existir, a deteccao retorna lista vazia sem quebrar o fluxo."
  ],
  "target_labels": [
    "bloco",
    "colonizacao",
    "contaminacao_visual"
  ],
  "dataset_classification": {
    "enabled": true,
    "applied": true,
    "dataset_class": "valid",
    "quality_status": "valid",
    "dataset_eligible": true,
    "target_image_path": "vision/dataset/raw/valid/snapshot_20260403T032011804645Z.jpg",
    "target_metadata_path": "vision/dataset/raw/valid/snapshot_20260403T032011804645Z.json",
    "method": "hardlink",
    "error": null
  },
  "remote_persistence": {
    "enabled": true,
    "remote_persisted": true,
    "storage_uploaded": true,
    "db_record_created": true,
    "image_storage_path": "vision/captures/2026/04/03/snapshot_20260403T032011804645Z.jpg",
    "record_id": "476a9c1d-bbd2-478c-8e18-c6eea86d2af7",
    "db_table": "vision_pipeline_runs",
    "retry_manifest_path": null,
    "error": null
  },
  "remote_persisted": true,
  "storage_uploaded": true,
  "db_record_created": true
}