{
  "executed_at": "2026-03-30T15:10:39.321202+00:00",
  "mode": "yolov8",
  "image_path": "vision/storage/artifacts/2026/03/30/snapshot_20260330T151011781625Z.jpg",
  "lote_id": null,
  "capture_metadata": {
    "captured_at": "2026-03-30T15:10:11.778020+00:00",
    "camera_url": "https://cam.cogumelos.net/capture",
    "http_status": 200,
    "content_type": "image/jpeg",
    "size_bytes": 44620,
    "source": "esp32-cam",
    "capture_attempt": 1,
    "capture_attempts_total": 3,
    "request_timeout_seconds": 15
  },
  "quality_check": {
    "status": "valid",
    "dataset_eligible": true,
    "metrics": {
      "resolution": {
        "width": 800,
        "height": 600,
        "total_pixels": 480000
      },
      "brightness_mean": 71.47,
      "contrast_stddev": 63.53,
      "sharpness_score": 12.72
    },
    "flags": {
      "low_resolution": false,
      "too_dark": false,
      "too_bright": false,
      "too_blurry": false,
      "invalid_image": false
    },
    "thresholds": {
      "min_width": 640,
      "min_height": 480,
      "too_dark_below": 55.0,
      "too_bright_above": 210.0,
      "too_blurry_below": 12.0
    },
    "error": null
  },
  "block_detection": {
    "enabled": true,
    "model": "/home/shroom/workspace/shroom-app/vision/models/block_detector_v2.pt",
    "model_path": "/home/shroom/workspace/shroom-app/vision/models/block_detector_v2.pt",
    "model_version": "v2",
    "used_fallback": false,
    "requested_model_path": "/home/shroom/workspace/shroom-app/vision/models/block_detector_v2.pt",
    "fallback_model_path": "/home/shroom/workspace/shroom-app/vision/models/block_detector.pt",
    "device": "cpu",
    "blocos_detectados": 11,
    "detections": [
      {
        "label": "bloco",
        "confidence": 0.9523,
        "bbox": [
          1.05,
          3.07,
          139.08,
          159.59
        ]
      },
      {
        "label": "bloco",
        "confidence": 0.8219,
        "bbox": [
          243.04,
          0.0,
          352.99,
          122.3
        ]
      },
      {
        "label": "bloco",
        "confidence": 0.7707,
        "bbox": [
          431.61,
          79.07,
          526.74,
          239.37
        ]
      },
      {
        "label": "bloco",
        "confidence": 0.769,
        "bbox": [
          365.71,
          79.04,
          445.07,
          261.42
        ]
      },
      {
        "label": "bloco",
        "confidence": 0.7476,
        "bbox": [
          286.43,
          143.23,
          372.66,
          280.36
        ]
      },
      {
        "label": "bloco",
        "confidence": 0.6818,
        "bbox": [
          115.16,
          2.04,
          234.32,
          153.96
        ]
      },
      {
        "label": "bloco",
        "confidence": 0.675,
        "bbox": [
          205.81,
          123.76,
          297.3,
          299.41
        ]
      },
      {
        "label": "bloco",
        "confidence": 0.5558,
        "bbox": [
          348.84,
          265.16,
          408.05,
          382.01
        ]
      },
      {
        "label": "bloco",
        "confidence": 0.5301,
        "bbox": [
          307.48,
          289.75,
          355.9,
          352.8
        ]
      },
      {
        "label": "bloco",
        "confidence": 0.5052,
        "bbox": [
          403.88,
          251.39,
          483.15,
          364.77
        ]
      },
      {
        "label": "bloco",
        "confidence": 0.3369,
        "bbox": [
          465.77,
          225.68,
          540.02,
          349.19
        ]
      }
    ],
    "error": null,
    "python_executable": "/home/shroom/workspace/shroom-app/.venv311/bin/python3",
    "python_version": "3.11.9 (main, Mar 18 2026, 22:08:28) [GCC 14.2.0]"
  },
  "summary": {
    "lote_id": null,
    "blocos_detectados": 11,
    "confianca_media_blocos": 0.6678,
    "block_detection_error": null,
    "contaminacao_visual_detectada": false,
    "colonizacao_estimada": null,
    "quality_status": "valid",
    "dataset_eligible": true,
    "dataset_class": "valid",
    "remote_persisted": true
  },
  "detections": [
    {
      "label": "bloco",
      "confidence": 0.9523,
      "bbox": [
        1.05,
        3.07,
        139.08,
        159.59
      ]
    },
    {
      "label": "bloco",
      "confidence": 0.8219,
      "bbox": [
        243.04,
        0.0,
        352.99,
        122.3
      ]
    },
    {
      "label": "bloco",
      "confidence": 0.7707,
      "bbox": [
        431.61,
        79.07,
        526.74,
        239.37
      ]
    },
    {
      "label": "bloco",
      "confidence": 0.769,
      "bbox": [
        365.71,
        79.04,
        445.07,
        261.42
      ]
    },
    {
      "label": "bloco",
      "confidence": 0.7476,
      "bbox": [
        286.43,
        143.23,
        372.66,
        280.36
      ]
    },
    {
      "label": "bloco",
      "confidence": 0.6818,
      "bbox": [
        115.16,
        2.04,
        234.32,
        153.96
      ]
    },
    {
      "label": "bloco",
      "confidence": 0.675,
      "bbox": [
        205.81,
        123.76,
        297.3,
        299.41
      ]
    },
    {
      "label": "bloco",
      "confidence": 0.5558,
      "bbox": [
        348.84,
        265.16,
        408.05,
        382.01
      ]
    },
    {
      "label": "bloco",
      "confidence": 0.5301,
      "bbox": [
        307.48,
        289.75,
        355.9,
        352.8
      ]
    },
    {
      "label": "bloco",
      "confidence": 0.5052,
      "bbox": [
        403.88,
        251.39,
        483.15,
        364.77
      ]
    },
    {
      "label": "bloco",
      "confidence": 0.3369,
      "bbox": [
        465.77,
        225.68,
        540.02,
        349.19
      ]
    }
  ],
  "notes": [
    "Pipeline executado com quality check local e detector inicial de blocos.",
    "A deteccao de colonizacao e contaminacao_visual ainda nao esta implementada.",
    "Se o modelo YOLO nao existir, a deteccao retorna lista vazia sem quebrar o fluxo."
  ],
  "target_labels": [
    "bloco",
    "colonizacao",
    "contaminacao_visual"
  ],
  "dataset_classification": {
    "enabled": true,
    "applied": true,
    "dataset_class": "valid",
    "quality_status": "valid",
    "dataset_eligible": true,
    "target_image_path": "vision/dataset/raw/valid/snapshot_20260330T151011781625Z.jpg",
    "target_metadata_path": "vision/dataset/raw/valid/snapshot_20260330T151011781625Z.json",
    "method": "hardlink",
    "error": null
  },
  "remote_persistence": {
    "enabled": true,
    "remote_persisted": true,
    "storage_uploaded": true,
    "db_record_created": true,
    "image_storage_path": "vision/captures/2026/03/30/snapshot_20260330T151011781625Z.jpg",
    "record_id": "9cdef7af-5b77-48da-89fd-8678d2644b2f",
    "db_table": "vision_pipeline_runs",
    "retry_manifest_path": null,
    "error": null
  },
  "remote_persisted": true,
  "storage_uploaded": true,
  "db_record_created": true
}